[
    {
        "CURRENCY": "UNITED STATES DOLLAR",
        "SYMBOL": "USD/INR",
        "TT BUY": 74.85,
        "TT SELL": 76.35,
        "BILL BUY": 74.79,
        "BILL SELL": 76.51,
        "TC BUY": 74.2,
        "TC SELL": 76.75,
        "CN BUY": 73.9,
        "CN SELL": 76.9,
        "PC BUY": 74.74
    },
    {
        "CURRENCY": "EURO",
        "SYMBOL": "EUR/INR",
        "TT BUY": 83.98,
        "TT SELL": 86.86,
        "BILL BUY": 83.91,
        "BILL SELL": 87.03,
        "TC BUY": 83.15,
        "TC SELL": 87.3,
        "CN BUY": 82.75,
        "CN SELL": 87.5,
        "PC BUY": 83.85
    },
    {
        "CURRENCY": "GREAT BRITAIN POUND",
        "SYMBOL": "GBP/INR",
        "TT BUY": 98.43,
        "TT SELL": 101.6,
        "BILL BUY": 98.35,
        "BILL SELL": 101.8,
        "TC BUY": 97.5,
        "TC SELL": 102.1,
        "CN BUY": 97.0,
        "CN SELL": 102.35,
        "PC BUY": 98.28
    },
    {
        "CURRENCY": "JAPANESE YEN",
        "SYMBOL": "JPY/INR",
        "TT BUY": 65.5,
        "TT SELL": 67.73,
        "BILL BUY": 65.44,
        "BILL SELL": 67.86,
        "TC BUY": 64.85,
        "TC SELL": 68.05,
        "CN BUY": 62.35,
        "CN SELL": 70.25,
        "PC BUY": 65.4
    },
    {
        "CURRENCY": "SWISS FRANC",
        "SYMBOL": "CHF/INR",
        "TT BUY": 80.35,
        "TT SELL": 83.36,
        "BILL BUY": 80.29,
        "BILL SELL": 83.53,
        "TC BUY": 79.6,
        "TC SELL": 83.8,
        "CN BUY": 76.55,
        "CN SELL": 86.5,
        "PC BUY": 80.23
    },
    {
        "CURRENCY": "AUSTRALIAN DOLLAR",
        "SYMBOL": "AUD/INR",
        "TT BUY": 53.07,
        "TT SELL": 55.28,
        "BILL BUY": 53.03,
        "BILL SELL": 55.39,
        "TC BUY": 53.05,
        "TC SELL": 55.55,
        "CN BUY": 51.0,
        "CN SELL": 57.35,
        "PC BUY": 52.99
    },
    {
        "CURRENCY": "NEW ZEALAND DOLLAR",
        "SYMBOL": "NZD/INR",
        "TT BUY": 50.52,
        "TT SELL": 52.73,
        "BILL BUY": 50.48,
        "BILL SELL": 52.83,
        "TC BUY": 0.0,
        "TC SELL": 0.0,
        "CN BUY": 48.05,
        "CN SELL": 54.7,
        "PC BUY": 50.44
    },
    {
        "CURRENCY": "CANADIAN DOLLAR",
        "SYMBOL": "CAD/INR",
        "TT BUY": 58.57,
        "TT SELL": 60.51,
        "BILL BUY": 58.52,
        "BILL SELL": 60.63,
        "TC BUY": 58.0,
        "TC SELL": 60.8,
        "CN BUY": 55.75,
        "CN SELL": 62.8,
        "PC BUY": 58.48
    },
    {
        "CURRENCY": "SINGAPORE DOLLAR",
        "SYMBOL": "SGD/INR",
        "TT BUY": 54.52,
        "TT SELL": 56.23,
        "BILL BUY": 54.47,
        "BILL SELL": 56.34,
        "TC BUY": 0.0,
        "TC SELL": 0.0,
        "CN BUY": 51.85,
        "CN SELL": 58.35,
        "PC BUY": 54.44
    },
    {
        "CURRENCY": "HONG KONG DOLLAR",
        "SYMBOL": "HKD/INR",
        "TT BUY": 9.54,
        "TT SELL": 9.85,
        "BILL BUY": 9.52,
        "BILL SELL": 9.87,
        "TC BUY": 0.0,
        "TC SELL": 0.0,
        "CN BUY": 9.05,
        "CN SELL": 10.2,
        "PC BUY": 9.51
    },
    {
        "CURRENCY": "DANISH KRONER",
        "SYMBOL": "DKK/INR",
        "TT BUY": 11.31,
        "TT SELL": 11.68,
        "BILL BUY": 11.29,
        "BILL SELL": 11.7,
        "TC BUY": 0.0,
        "TC SELL": 0.0,
        "CN BUY": 10.75,
        "CN SELL": 12.15,
        "PC BUY": 11.29
    },
    {
        "CURRENCY": "NORWEGIAN KRONER",
        "SYMBOL": "NOK/INR",
        "TT BUY": 8.28,
        "TT SELL": 8.55,
        "BILL BUY": 8.27,
        "BILL SELL": 8.56,
        "TC BUY": 0.0,
        "TC SELL": 0.0,
        "CN BUY": 7.9,
        "CN SELL": 8.9,
        "PC BUY": 8.25
    },
    {
        "CURRENCY": "SWEDISH KRONA",
        "SYMBOL": "SEK/INR",
        "TT BUY": 8.22,
        "TT SELL": 8.48,
        "BILL BUY": 8.21,
        "BILL SELL": 8.5,
        "TC BUY": 0.0,
        "TC SELL": 0.0,
        "CN BUY": 7.8,
        "CN SELL": 8.85,
        "PC BUY": 8.19
    },
    {
        "CURRENCY": "BAHRAINI DINAR",
        "SYMBOL": "BHD/INR",
        "TT BUY": 194.62,
        "TT SELL": 206.67,
        "BILL BUY": 194.47,
        "BILL SELL": 207.08,
        "TC BUY": 0.0,
        "TC SELL": 0.0,
        "CN BUY": 189.2,
        "CN SELL": 210.2,
        "PC BUY": 194.33
    },
    {
        "CURRENCY": "KUWAITI DINAR",
        "SYMBOL": "KWD/INR",
        "TT BUY": 242.02,
        "TT SELL": 257.64,
        "BILL BUY": 241.82,
        "BILL SELL": 258.15,
        "TC BUY": 0.0,
        "TC SELL": 0.0,
        "CN BUY": 235.3,
        "CN SELL": 262.05,
        "PC BUY": 241.66
    },
    {
        "CURRENCY": "UAE DIRHAM",
        "SYMBOL": "AED/INR",
        "TT BUY": 19.98,
        "TT SELL": 21.22,
        "BILL BUY": 19.96,
        "BILL SELL": 21.26,
        "TC BUY": 0.0,
        "TC SELL": 0.0,
        "CN BUY": 19.4,
        "CN SELL": 21.6,
        "PC BUY": 19.95
    },
    {
        "CURRENCY": "SAUDI ARABIAN RIYAL",
        "SYMBOL": "SAR/INR",
        "TT BUY": 19.56,
        "TT SELL": 20.77,
        "BILL BUY": 19.55,
        "BILL SELL": 20.81,
        "TC BUY": 0.0,
        "TC SELL": 0.0,
        "CN BUY": 19.0,
        "CN SELL": 21.1,
        "PC BUY": 19.53
    },
    {
        "CURRENCY": "SOUTH AFRICAN RAND",
        "SYMBOL": "ZAR/INR",
        "TT BUY": 4.59,
        "TT SELL": 4.88,
        "BILL BUY": 4.58,
        "BILL SELL": 4.89,
        "TC BUY": 0.0,
        "TC SELL": 0.0,
        "CN BUY": 4.35,
        "CN SELL": 4.95,
        "PC BUY": 4.57
    },
    {
        "CURRENCY": "CHINESE YUAN",
        "SYMBOL": "CNY/INR",
        "TT BUY": 0.0,
        "TT SELL": 0.0,
        "BILL BUY": 11.7,
        "BILL SELL": 12.07,
        "TC BUY": 0.0,
        "TC SELL": 0.0,
        "CN BUY": 0.0,
        "CN SELL": 0.0,
        "PC BUY": 0.0
    },
    {
        "CURRENCY": "OMANI RIYAL",
        "SYMBOL": "OMR/INR",
        "TT BUY": 190.59,
        "TT SELL": 202.39,
        "BILL BUY": 190.44,
        "BILL SELL": 202.79,
        "TC BUY": 0.0,
        "TC SELL": 0.0,
        "CN BUY": 185.3,
        "CN SELL": 205.85,
        "PC BUY": 0.0
    },
    {
        "CURRENCY": "QATARI RIAL",
        "SYMBOL": "QAR/INR",
        "TT BUY": 20.15,
        "TT SELL": 21.41,
        "BILL BUY": 20.13,
        "BILL SELL": 21.45,
        "TC BUY": 0.0,
        "TC SELL": 0.0,
        "CN BUY": 19.6,
        "CN SELL": 21.75,
        "PC BUY": 20.12
    },
    {
        "CURRENCY": "MALAYSIAN RINGGIT",
        "SYMBOL": "MYR/INR",
        "TT BUY": 0.0,
        "TT SELL": 0.0,
        "BILL BUY": 0.0,
        "BILL SELL": 0.0,
        "TC BUY": 0.0,
        "TC SELL": 0.0,
        "CN BUY": 16.7,
        "CN SELL": 19.0,
        "PC BUY": 0.0
    },
    {
        "CURRENCY": "THAI BAHT",
        "SYMBOL": "THB/INR",
        "TT BUY": 0.0,
        "TT SELL": 0.0,
        "BILL BUY": 0.0,
        "BILL SELL": 0.0,
        "TC BUY": 0.0,
        "TC SELL": 0.0,
        "CN BUY": 211.85,
        "CN SELL": 236.35,
        "PC BUY": 0.0
    },
    {
        "CURRENCY": "PAKISTANI RUPEE",
        "SYMBOL": "PKR/INR",
        "TT BUY": 0.0,
        "TT SELL": 0.0,
        "BILL BUY": 0.0,
        "BILL SELL": 0.0,
        "TC BUY": 0.0,
        "TC SELL": 0.0,
        "CN BUY": 0.35,
        "CN SELL": 0.42,
        "PC BUY": 0.0
    },
    {
        "CURRENCY": "BANGLADESHI TAKA",
        "SYMBOL": "BDT/INR",
        "TT BUY": 0.0,
        "TT SELL": 0.0,
        "BILL BUY": 0.0,
        "BILL SELL": 0.0,
        "TC BUY": 0.0,
        "TC SELL": 0.0,
        "CN BUY": 0.73,
        "CN SELL": 0.88,
        "PC BUY": 0.0
    },
    {
        "CURRENCY": "TURKISH LIRA",
        "SYMBOL": "TRY/INR",
        "TT BUY": 0.0,
        "TT SELL": 0.0,
        "BILL BUY": 5.31,
        "BILL SELL": 5.66,
        "TC BUY": 0.0,
        "TC SELL": 0.0,
        "CN BUY": 0.0,
        "CN SELL": 0.0,
        "PC BUY": 0.0
    },
    {
        "CURRENCY": "KOREAN WON",
        "SYMBOL": "KRW/INR",
        "TT BUY": 0.0,
        "TT SELL": 0.0,
        "BILL BUY": 6.23,
        "BILL SELL": 6.63,
        "TC BUY": 0.0,
        "TC SELL": 0.0,
        "CN BUY": 0.0,
        "CN SELL": 0.0,
        "PC BUY": 0.0
    }
]