[
    {
        "CURRENCY": "UNITED STATES DOLLAR",
        "SYMBOL": "USD/INR",
        "TT BUY": 74.75,
        "TT SELL": 76.25,
        "BILL BUY": 74.69,
        "BILL SELL": 76.41,
        "TC BUY": 74.1,
        "TC SELL": 76.65,
        "CN BUY": 73.8,
        "CN SELL": 76.8,
        "PC BUY": 74.64
    },
    {
        "CURRENCY": "EURO",
        "SYMBOL": "EUR/INR",
        "TT BUY": 84.21,
        "TT SELL": 87.09,
        "BILL BUY": 84.14,
        "BILL SELL": 87.26,
        "TC BUY": 83.4,
        "TC SELL": 87.55,
        "CN BUY": 83.0,
        "CN SELL": 87.75,
        "PC BUY": 84.08
    },
    {
        "CURRENCY": "GREAT BRITAIN POUND",
        "SYMBOL": "GBP/INR",
        "TT BUY": 94.67,
        "TT SELL": 97.73,
        "BILL BUY": 94.59,
        "BILL SELL": 97.92,
        "TC BUY": 93.75,
        "TC SELL": 98.2,
        "CN BUY": 93.3,
        "CN SELL": 98.45,
        "PC BUY": 94.53
    },
    {
        "CURRENCY": "JAPANESE YEN",
        "SYMBOL": "JPY/INR",
        "TT BUY": 68.93,
        "TT SELL": 71.34,
        "BILL BUY": 68.88,
        "BILL SELL": 71.48,
        "TC BUY": 68.25,
        "TC SELL": 71.7,
        "CN BUY": 65.6,
        "CN SELL": 74.05,
        "PC BUY": 68.83
    },
    {
        "CURRENCY": "SWISS FRANC",
        "SYMBOL": "CHF/INR",
        "TT BUY": 77.99,
        "TT SELL": 80.87,
        "BILL BUY": 77.92,
        "BILL SELL": 81.03,
        "TC BUY": 77.25,
        "TC SELL": 81.25,
        "CN BUY": 74.25,
        "CN SELL": 83.9,
        "PC BUY": 77.87
    },
    {
        "CURRENCY": "AUSTRALIAN DOLLAR",
        "SYMBOL": "AUD/INR",
        "TT BUY": 51.65,
        "TT SELL": 53.8,
        "BILL BUY": 51.61,
        "BILL SELL": 53.91,
        "TC BUY": 51.6,
        "TC SELL": 54.05,
        "CN BUY": 49.6,
        "CN SELL": 55.8,
        "PC BUY": 51.57
    },
    {
        "CURRENCY": "NEW ZEALAND DOLLAR",
        "SYMBOL": "NZD/INR",
        "TT BUY": 48.4,
        "TT SELL": 50.56,
        "BILL BUY": 48.36,
        "BILL SELL": 50.66,
        "TC BUY": 0.0,
        "TC SELL": 0.0,
        "CN BUY": 46.05,
        "CN SELL": 52.45,
        "PC BUY": 48.33
    },
    {
        "CURRENCY": "CANADIAN DOLLAR",
        "SYMBOL": "CAD/INR",
        "TT BUY": 55.45,
        "TT SELL": 57.27,
        "BILL BUY": 55.41,
        "BILL SELL": 57.39,
        "TC BUY": 54.9,
        "TC SELL": 57.55,
        "CN BUY": 52.8,
        "CN SELL": 59.4,
        "PC BUY": 55.37
    },
    {
        "CURRENCY": "SINGAPORE DOLLAR",
        "SYMBOL": "SGD/INR",
        "TT BUY": 53.57,
        "TT SELL": 55.26,
        "BILL BUY": 53.52,
        "BILL SELL": 55.37,
        "TC BUY": 0.0,
        "TC SELL": 0.0,
        "CN BUY": 51.0,
        "CN SELL": 57.35,
        "PC BUY": 53.49
    },
    {
        "CURRENCY": "HONG KONG DOLLAR",
        "SYMBOL": "HKD/INR",
        "TT BUY": 9.58,
        "TT SELL": 9.9,
        "BILL BUY": 9.57,
        "BILL SELL": 9.92,
        "TC BUY": 0.0,
        "TC SELL": 0.0,
        "CN BUY": 9.1,
        "CN SELL": 10.25,
        "PC BUY": 9.55
    },
    {
        "CURRENCY": "DANISH KRONER",
        "SYMBOL": "DKK/INR",
        "TT BUY": 11.31,
        "TT SELL": 11.68,
        "BILL BUY": 11.29,
        "BILL SELL": 11.7,
        "TC BUY": 0.0,
        "TC SELL": 0.0,
        "CN BUY": 10.75,
        "CN SELL": 12.15,
        "PC BUY": 11.29
    },
    {
        "CURRENCY": "NORWEGIAN KRONER",
        "SYMBOL": "NOK/INR",
        "TT BUY": 8.03,
        "TT SELL": 8.28,
        "BILL BUY": 8.02,
        "BILL SELL": 8.3,
        "TC BUY": 0.0,
        "TC SELL": 0.0,
        "CN BUY": 7.65,
        "CN SELL": 8.6,
        "PC BUY": 8.0
    },
    {
        "CURRENCY": "SWEDISH KRONA",
        "SYMBOL": "SEK/INR",
        "TT BUY": 8.09,
        "TT SELL": 8.35,
        "BILL BUY": 8.07,
        "BILL SELL": 8.36,
        "TC BUY": 0.0,
        "TC SELL": 0.0,
        "CN BUY": 7.7,
        "CN SELL": 8.65,
        "PC BUY": 8.06
    },
    {
        "CURRENCY": "BAHRAINI DINAR",
        "SYMBOL": "BHD/INR",
        "TT BUY": 193.87,
        "TT SELL": 206.3,
        "BILL BUY": 193.72,
        "BILL SELL": 206.71,
        "TC BUY": 0.0,
        "TC SELL": 0.0,
        "CN BUY": 188.45,
        "CN SELL": 209.8,
        "PC BUY": 193.58
    },
    {
        "CURRENCY": "KUWAITI DINAR",
        "SYMBOL": "KWD/INR",
        "TT BUY": 238.0,
        "TT SELL": 252.8,
        "BILL BUY": 237.81,
        "BILL SELL": 253.3,
        "TC BUY": 0.0,
        "TC SELL": 0.0,
        "CN BUY": 231.35,
        "CN SELL": 257.1,
        "PC BUY": 237.64
    },
    {
        "CURRENCY": "UAE DIRHAM",
        "SYMBOL": "AED/INR",
        "TT BUY": 19.95,
        "TT SELL": 21.19,
        "BILL BUY": 19.93,
        "BILL SELL": 21.23,
        "TC BUY": 0.0,
        "TC SELL": 0.0,
        "CN BUY": 19.4,
        "CN SELL": 21.55,
        "PC BUY": 19.92
    },
    {
        "CURRENCY": "SAUDI ARABIAN RIYAL",
        "SYMBOL": "SAR/INR",
        "TT BUY": 19.53,
        "TT SELL": 20.74,
        "BILL BUY": 19.51,
        "BILL SELL": 20.78,
        "TC BUY": 0.0,
        "TC SELL": 0.0,
        "CN BUY": 19.0,
        "CN SELL": 21.1,
        "PC BUY": 19.5
    },
    {
        "CURRENCY": "SOUTH AFRICAN RAND",
        "SYMBOL": "ZAR/INR",
        "TT BUY": 4.41,
        "TT SELL": 4.69,
        "BILL BUY": 4.4,
        "BILL SELL": 4.7,
        "TC BUY": 0.0,
        "TC SELL": 0.0,
        "CN BUY": 4.25,
        "CN SELL": 4.8,
        "PC BUY": 4.39
    },
    {
        "CURRENCY": "CHINESE YUAN",
        "SYMBOL": "CNY/INR",
        "TT BUY": 0.0,
        "TT SELL": 0.0,
        "BILL BUY": 10.52,
        "BILL SELL": 10.84,
        "TC BUY": 0.0,
        "TC SELL": 0.0,
        "CN BUY": 0.0,
        "CN SELL": 0.0,
        "PC BUY": 0.0
    },
    {
        "CURRENCY": "OMANI RIYAL",
        "SYMBOL": "OMR/INR",
        "TT BUY": 190.34,
        "TT SELL": 202.15,
        "BILL BUY": 0.0,
        "BILL SELL": 0.0,
        "TC BUY": 0.0,
        "TC SELL": 0.0,
        "CN BUY": 185.05,
        "CN SELL": 205.6,
        "PC BUY": 0.0
    },
    {
        "CURRENCY": "QATARI RIAL",
        "SYMBOL": "QAR/INR",
        "TT BUY": 20.12,
        "TT SELL": 21.38,
        "BILL BUY": 20.11,
        "BILL SELL": 21.42,
        "TC BUY": 0.0,
        "TC SELL": 0.0,
        "CN BUY": 19.55,
        "CN SELL": 21.75,
        "PC BUY": 20.09
    },
    {
        "CURRENCY": "MALAYSIAN RINGGIT",
        "SYMBOL": "MYR/INR",
        "TT BUY": 0.0,
        "TT SELL": 0.0,
        "BILL BUY": 0.0,
        "BILL SELL": 0.0,
        "TC BUY": 0.0,
        "TC SELL": 0.0,
        "CN BUY": 16.5,
        "CN SELL": 18.75,
        "PC BUY": 0.0
    },
    {
        "CURRENCY": "THAI BAHT",
        "SYMBOL": "THB/INR",
        "TT BUY": 0.0,
        "TT SELL": 0.0,
        "BILL BUY": 0.0,
        "BILL SELL": 0.0,
        "TC BUY": 0.0,
        "TC SELL": 0.0,
        "CN BUY": 227.95,
        "CN SELL": 254.3,
        "PC BUY": 0.0
    },
    {
        "CURRENCY": "PAKISTANI RUPEE",
        "SYMBOL": "PKR/INR",
        "TT BUY": 0.0,
        "TT SELL": 0.0,
        "BILL BUY": 0.0,
        "BILL SELL": 0.0,
        "TC BUY": 0.0,
        "TC SELL": 0.0,
        "CN BUY": 0.38,
        "CN SELL": 0.46,
        "PC BUY": 0.0
    },
    {
        "CURRENCY": "BANGLADESHI TAKA",
        "SYMBOL": "BDT/INR",
        "TT BUY": 0.0,
        "TT SELL": 0.0,
        "BILL BUY": 0.0,
        "BILL SELL": 0.0,
        "TC BUY": 0.0,
        "TC SELL": 0.0,
        "CN BUY": 0.74,
        "CN SELL": 0.89,
        "PC BUY": 0.0
    },
    {
        "CURRENCY": "TURKISH LIRA",
        "SYMBOL": "TRY/INR",
        "TT BUY": 0.0,
        "TT SELL": 0.0,
        "BILL BUY": 10.78,
        "BILL SELL": 11.47,
        "TC BUY": 0.0,
        "TC SELL": 0.0,
        "CN BUY": 0.0,
        "CN SELL": 0.0,
        "PC BUY": 0.0
    },
    {
        "CURRENCY": "KOREAN WON",
        "SYMBOL": "KRW/INR",
        "TT BUY": 0.0,
        "TT SELL": 0.0,
        "BILL BUY": 6.14,
        "BILL SELL": 6.54,
        "TC BUY": 0.0,
        "TC SELL": 0.0,
        "CN BUY": 0.0,
        "CN SELL": 0.0,
        "PC BUY": 0.0
    }
]