[
    {
        "CURRENCY": "UNITED STATES DOLLAR",
        "SYMBOL": "USD/INR",
        "TT BUY": 80.55,
        "TT SELL": 82.05,
        "BILL BUY": 80.48,
        "BILL SELL": 82.22,
        "TC BUY": 79.8,
        "TC SELL": 82.45,
        "CN BUY": 79.5,
        "CN SELL": 82.6,
        "PC BUY": 80.42
    },
    {
        "CURRENCY": "EURO",
        "SYMBOL": "EUR/INR",
        "TT BUY": 80.54,
        "TT SELL": 83.33,
        "BILL BUY": 80.48,
        "BILL SELL": 83.49,
        "TC BUY": 79.75,
        "TC SELL": 83.75,
        "CN BUY": 79.35,
        "CN SELL": 83.95,
        "PC BUY": 80.42
    },
    {
        "CURRENCY": "GREAT BRITAIN POUND",
        "SYMBOL": "GBP/INR",
        "TT BUY": 92.5,
        "TT SELL": 95.48,
        "BILL BUY": 92.43,
        "BILL SELL": 95.66,
        "TC BUY": 91.6,
        "TC SELL": 95.95,
        "CN BUY": 91.15,
        "CN SELL": 96.2,
        "PC BUY": 92.36
    },
    {
        "CURRENCY": "JAPANESE YEN",
        "SYMBOL": "JPY/INR",
        "TT BUY": 55.11,
        "TT SELL": 56.75,
        "BILL BUY": 55.07,
        "BILL SELL": 56.86,
        "TC BUY": 54.6,
        "TC SELL": 57.05,
        "CN BUY": 52.5,
        "CN SELL": 58.9,
        "PC BUY": 55.03
    },
    {
        "CURRENCY": "SWISS FRANC",
        "SYMBOL": "CHF/INR",
        "TT BUY": 81.27,
        "TT SELL": 84.08,
        "BILL BUY": 81.21,
        "BILL SELL": 84.24,
        "TC BUY": 80.5,
        "TC SELL": 84.5,
        "CN BUY": 77.4,
        "CN SELL": 87.25,
        "PC BUY": 81.15
    },
    {
        "CURRENCY": "AUSTRALIAN DOLLAR",
        "SYMBOL": "AUD/INR",
        "TT BUY": 51.95,
        "TT SELL": 54.12,
        "BILL BUY": 51.91,
        "BILL SELL": 54.22,
        "TC BUY": 51.95,
        "TC SELL": 54.4,
        "CN BUY": 49.95,
        "CN SELL": 56.15,
        "PC BUY": 51.87
    },
    {
        "CURRENCY": "NEW ZEALAND DOLLAR",
        "SYMBOL": "NZD/INR",
        "TT BUY": 47.52,
        "TT SELL": 49.65,
        "BILL BUY": 47.48,
        "BILL SELL": 49.74,
        "TC BUY": 0.0,
        "TC SELL": 0.0,
        "CN BUY": 45.25,
        "CN SELL": 51.5,
        "PC BUY": 47.45
    },
    {
        "CURRENCY": "CANADIAN DOLLAR",
        "SYMBOL": "CAD/INR",
        "TT BUY": 59.64,
        "TT SELL": 61.51,
        "BILL BUY": 59.59,
        "BILL SELL": 61.63,
        "TC BUY": 59.05,
        "TC SELL": 61.8,
        "CN BUY": 56.75,
        "CN SELL": 63.8,
        "PC BUY": 59.55
    },
    {
        "CURRENCY": "SINGAPORE DOLLAR",
        "SYMBOL": "SGD/INR",
        "TT BUY": 57.36,
        "TT SELL": 59.1,
        "BILL BUY": 57.32,
        "BILL SELL": 59.21,
        "TC BUY": 0.0,
        "TC SELL": 0.0,
        "CN BUY": 54.6,
        "CN SELL": 61.35,
        "PC BUY": 57.27
    },
    {
        "CURRENCY": "HONG KONG DOLLAR",
        "SYMBOL": "HKD/INR",
        "TT BUY": 10.2,
        "TT SELL": 10.52,
        "BILL BUY": 10.18,
        "BILL SELL": 10.54,
        "TC BUY": 0.0,
        "TC SELL": 0.0,
        "CN BUY": 9.7,
        "CN SELL": 10.9,
        "PC BUY": 10.17
    },
    {
        "CURRENCY": "DANISH KRONER",
        "SYMBOL": "DKK/INR",
        "TT BUY": 10.85,
        "TT SELL": 11.18,
        "BILL BUY": 10.84,
        "BILL SELL": 11.2,
        "TC BUY": 0.0,
        "TC SELL": 0.0,
        "CN BUY": 10.35,
        "CN SELL": 11.6,
        "PC BUY": 10.83
    },
    {
        "CURRENCY": "NORWEGIAN KRONER",
        "SYMBOL": "NOK/INR",
        "TT BUY": 7.83,
        "TT SELL": 8.06,
        "BILL BUY": 7.82,
        "BILL SELL": 8.08,
        "TC BUY": 0.0,
        "TC SELL": 0.0,
        "CN BUY": 7.45,
        "CN SELL": 8.35,
        "PC BUY": 7.8
    },
    {
        "CURRENCY": "SWEDISH KRONA",
        "SYMBOL": "SEK/INR",
        "TT BUY": 7.47,
        "TT SELL": 7.69,
        "BILL BUY": 7.46,
        "BILL SELL": 7.7,
        "TC BUY": 0.0,
        "TC SELL": 0.0,
        "CN BUY": 7.1,
        "CN SELL": 8.0,
        "PC BUY": 7.44
    },
    {
        "CURRENCY": "BAHRAINI DINAR",
        "SYMBOL": "BHD/INR",
        "TT BUY": 209.5,
        "TT SELL": 222.17,
        "BILL BUY": 209.29,
        "BILL SELL": 222.6,
        "TC BUY": 0.0,
        "TC SELL": 0.0,
        "CN BUY": 203.5,
        "CN SELL": 225.9,
        "PC BUY": 209.14
    },
    {
        "CURRENCY": "KUWAITI DINAR",
        "SYMBOL": "KWD/INR",
        "TT BUY": 255.5,
        "TT SELL": 271.04,
        "BILL BUY": 255.31,
        "BILL SELL": 271.57,
        "TC BUY": 0.0,
        "TC SELL": 0.0,
        "CN BUY": 248.3,
        "CN SELL": 275.6,
        "PC BUY": 255.12
    },
    {
        "CURRENCY": "UAE DIRHAM",
        "SYMBOL": "AED/INR",
        "TT BUY": 21.5,
        "TT SELL": 22.8,
        "BILL BUY": 21.48,
        "BILL SELL": 22.84,
        "TC BUY": 0.0,
        "TC SELL": 0.0,
        "CN BUY": 20.9,
        "CN SELL": 23.2,
        "PC BUY": 21.47
    },
    {
        "CURRENCY": "SAUDI ARABIAN RIYAL",
        "SYMBOL": "SAR/INR",
        "TT BUY": 21.0,
        "TT SELL": 22.28,
        "BILL BUY": 20.99,
        "BILL SELL": 22.32,
        "TC BUY": 0.0,
        "TC SELL": 0.0,
        "CN BUY": 20.4,
        "CN SELL": 22.65,
        "PC BUY": 20.97
    },
    {
        "CURRENCY": "SOUTH AFRICAN RAND",
        "SYMBOL": "ZAR/INR",
        "TT BUY": 4.47,
        "TT SELL": 4.74,
        "BILL BUY": 4.46,
        "BILL SELL": 4.75,
        "TC BUY": 0.0,
        "TC SELL": 0.0,
        "CN BUY": 4.3,
        "CN SELL": 4.85,
        "PC BUY": 4.45
    },
    {
        "CURRENCY": "CHINESE YUAN",
        "SYMBOL": "CNY/INR",
        "TT BUY": 0.0,
        "TT SELL": 0.0,
        "BILL BUY": 11.08,
        "BILL SELL": 11.4,
        "TC BUY": 0.0,
        "TC SELL": 0.0,
        "CN BUY": 0.0,
        "CN SELL": 0.0,
        "PC BUY": 0.0
    },
    {
        "CURRENCY": "OMANI RIYAL",
        "SYMBOL": "OMR/INR",
        "TT BUY": 205.1,
        "TT SELL": 218.06,
        "BILL BUY": 204.94,
        "BILL SELL": 218.48,
        "TC BUY": 0.0,
        "TC SELL": 0.0,
        "CN BUY": 199.3,
        "CN SELL": 221.7,
        "PC BUY": 0.0
    },
    {
        "CURRENCY": "QATARI RIAL",
        "SYMBOL": "QAR/INR",
        "TT BUY": 21.53,
        "TT SELL": 23.0,
        "BILL BUY": 21.51,
        "BILL SELL": 23.05,
        "TC BUY": 0.0,
        "TC SELL": 0.0,
        "CN BUY": 20.9,
        "CN SELL": 23.4,
        "PC BUY": 21.5
    },
    {
        "CURRENCY": "MALAYSIAN RINGGIT",
        "SYMBOL": "MYR/INR",
        "TT BUY": 0.0,
        "TT SELL": 0.0,
        "BILL BUY": 0.0,
        "BILL SELL": 0.0,
        "TC BUY": 0.0,
        "TC SELL": 0.0,
        "CN BUY": 16.2,
        "CN SELL": 18.35,
        "PC BUY": 0.0
    },
    {
        "CURRENCY": "THAI BAHT",
        "SYMBOL": "THB/INR",
        "TT BUY": 0.0,
        "TT SELL": 0.0,
        "BILL BUY": 0.0,
        "BILL SELL": 0.0,
        "TC BUY": 0.0,
        "TC SELL": 0.0,
        "CN BUY": 208.5,
        "CN SELL": 232.2,
        "PC BUY": 0.0
    },
    {
        "CURRENCY": "PAKISTANI RUPEE",
        "SYMBOL": "PKR/INR",
        "TT BUY": 0.0,
        "TT SELL": 0.0,
        "BILL BUY": 0.0,
        "BILL SELL": 0.0,
        "TC BUY": 0.0,
        "TC SELL": 0.0,
        "CN BUY": 0.3,
        "CN SELL": 0.36,
        "PC BUY": 0.0
    },
    {
        "CURRENCY": "BANGLADESHI TAKA",
        "SYMBOL": "BDT/INR",
        "TT BUY": 0.0,
        "TT SELL": 0.0,
        "BILL BUY": 0.0,
        "BILL SELL": 0.0,
        "TC BUY": 0.0,
        "TC SELL": 0.0,
        "CN BUY": 0.64,
        "CN SELL": 0.77,
        "PC BUY": 0.0
    },
    {
        "CURRENCY": "TURKISH LIRA",
        "SYMBOL": "TRY/INR",
        "TT BUY": 0.0,
        "TT SELL": 0.0,
        "BILL BUY": 4.24,
        "BILL SELL": 4.5,
        "TC BUY": 0.0,
        "TC SELL": 0.0,
        "CN BUY": 0.0,
        "CN SELL": 0.0,
        "PC BUY": 0.0
    },
    {
        "CURRENCY": "KOREAN WON",
        "SYMBOL": "KRW/INR",
        "TT BUY": 0.0,
        "TT SELL": 0.0,
        "BILL BUY": 5.79,
        "BILL SELL": 6.17,
        "TC BUY": 0.0,
        "TC SELL": 0.0,
        "CN BUY": 0.0,
        "CN SELL": 0.0,
        "PC BUY": 0.0
    }
]