[
    {
        "CURRENCY": "UNITED STATES DOLLAR",
        "SYMBOL": "USD/INR",
        "TT BUY": 81.9,
        "TT SELL": 83.4,
        "BILL BUY": 81.83,
        "BILL SELL": 83.57,
        "TC BUY": 81.1,
        "TC SELL": 83.85,
        "CN BUY": 80.8,
        "CN SELL": 84.0,
        "PC BUY": 81.77
    },
    {
        "CURRENCY": "EURO",
        "SYMBOL": "EUR/INR",
        "TT BUY": 79.39,
        "TT SELL": 82.13,
        "BILL BUY": 79.33,
        "BILL SELL": 82.29,
        "TC BUY": 78.65,
        "TC SELL": 82.55,
        "CN BUY": 78.25,
        "CN SELL": 82.75,
        "PC BUY": 79.27
    },
    {
        "CURRENCY": "GREAT BRITAIN POUND",
        "SYMBOL": "GBP/INR",
        "TT BUY": 91.18,
        "TT SELL": 94.14,
        "BILL BUY": 91.12,
        "BILL SELL": 94.33,
        "TC BUY": 90.3,
        "TC SELL": 94.6,
        "CN BUY": 89.85,
        "CN SELL": 94.85,
        "PC BUY": 91.04
    },
    {
        "CURRENCY": "JAPANESE YEN",
        "SYMBOL": "JPY/INR",
        "TT BUY": 55.03,
        "TT SELL": 56.63,
        "BILL BUY": 54.99,
        "BILL SELL": 56.75,
        "TC BUY": 54.5,
        "TC SELL": 56.9,
        "CN BUY": 52.4,
        "CN SELL": 58.75,
        "PC BUY": 54.95
    },
    {
        "CURRENCY": "SWISS FRANC",
        "SYMBOL": "CHF/INR",
        "TT BUY": 80.36,
        "TT SELL": 83.13,
        "BILL BUY": 80.3,
        "BILL SELL": 83.3,
        "TC BUY": 79.6,
        "TC SELL": 83.55,
        "CN BUY": 76.55,
        "CN SELL": 86.25,
        "PC BUY": 80.24
    },
    {
        "CURRENCY": "AUSTRALIAN DOLLAR",
        "SYMBOL": "AUD/INR",
        "TT BUY": 51.3,
        "TT SELL": 53.47,
        "BILL BUY": 51.27,
        "BILL SELL": 53.58,
        "TC BUY": 51.3,
        "TC SELL": 53.75,
        "CN BUY": 49.3,
        "CN SELL": 55.5,
        "PC BUY": 51.22
    },
    {
        "CURRENCY": "NEW ZEALAND DOLLAR",
        "SYMBOL": "NZD/INR",
        "TT BUY": 47.13,
        "TT SELL": 49.26,
        "BILL BUY": 47.09,
        "BILL SELL": 49.36,
        "TC BUY": 0.0,
        "TC SELL": 0.0,
        "CN BUY": 44.85,
        "CN SELL": 51.1,
        "PC BUY": 47.06
    },
    {
        "CURRENCY": "CANADIAN DOLLAR",
        "SYMBOL": "CAD/INR",
        "TT BUY": 59.43,
        "TT SELL": 61.27,
        "BILL BUY": 59.38,
        "BILL SELL": 61.4,
        "TC BUY": 58.85,
        "TC SELL": 61.6,
        "CN BUY": 56.6,
        "CN SELL": 63.6,
        "PC BUY": 59.34
    },
    {
        "CURRENCY": "SINGAPORE DOLLAR",
        "SYMBOL": "SGD/INR",
        "TT BUY": 57.47,
        "TT SELL": 59.18,
        "BILL BUY": 57.42,
        "BILL SELL": 59.3,
        "TC BUY": 0.0,
        "TC SELL": 0.0,
        "CN BUY": 54.7,
        "CN SELL": 61.45,
        "PC BUY": 57.38
    },
    {
        "CURRENCY": "HONG KONG DOLLAR",
        "SYMBOL": "HKD/INR",
        "TT BUY": 10.37,
        "TT SELL": 10.7,
        "BILL BUY": 10.35,
        "BILL SELL": 10.72,
        "TC BUY": 0.0,
        "TC SELL": 0.0,
        "CN BUY": 9.85,
        "CN SELL": 11.1,
        "PC BUY": 10.34
    },
    {
        "CURRENCY": "DANISH KRONER",
        "SYMBOL": "DKK/INR",
        "TT BUY": 10.69,
        "TT SELL": 11.01,
        "BILL BUY": 10.68,
        "BILL SELL": 11.03,
        "TC BUY": 0.0,
        "TC SELL": 0.0,
        "CN BUY": 10.15,
        "CN SELL": 11.4,
        "PC BUY": 10.67
    },
    {
        "CURRENCY": "NORWEGIAN KRONER",
        "SYMBOL": "NOK/INR",
        "TT BUY": 7.73,
        "TT SELL": 7.96,
        "BILL BUY": 7.72,
        "BILL SELL": 7.98,
        "TC BUY": 0.0,
        "TC SELL": 0.0,
        "CN BUY": 7.35,
        "CN SELL": 8.25,
        "PC BUY": 7.7
    },
    {
        "CURRENCY": "SWEDISH KRONA",
        "SYMBOL": "SEK/INR",
        "TT BUY": 7.3,
        "TT SELL": 7.51,
        "BILL BUY": 7.29,
        "BILL SELL": 7.53,
        "TC BUY": 0.0,
        "TC SELL": 0.0,
        "CN BUY": 6.9,
        "CN SELL": 7.8,
        "PC BUY": 7.27
    },
    {
        "CURRENCY": "BAHRAINI DINAR",
        "SYMBOL": "BHD/INR",
        "TT BUY": 212.9,
        "TT SELL": 225.79,
        "BILL BUY": 212.77,
        "BILL SELL": 226.25,
        "TC BUY": 0.0,
        "TC SELL": 0.0,
        "CN BUY": 206.8,
        "CN SELL": 229.7,
        "PC BUY": 212.61
    },
    {
        "CURRENCY": "KUWAITI DINAR",
        "SYMBOL": "KWD/INR",
        "TT BUY": 258.5,
        "TT SELL": 274.12,
        "BILL BUY": 258.27,
        "BILL SELL": 274.68,
        "TC BUY": 0.0,
        "TC SELL": 0.0,
        "CN BUY": 251.0,
        "CN SELL": 278.8,
        "PC BUY": 258.07
    },
    {
        "CURRENCY": "UAE DIRHAM",
        "SYMBOL": "AED/INR",
        "TT BUY": 21.85,
        "TT SELL": 23.18,
        "BILL BUY": 21.84,
        "BILL SELL": 23.22,
        "TC BUY": 0.0,
        "TC SELL": 0.0,
        "CN BUY": 21.25,
        "CN SELL": 23.55,
        "PC BUY": 21.82
    },
    {
        "CURRENCY": "SAUDI ARABIAN RIYAL",
        "SYMBOL": "SAR/INR",
        "TT BUY": 21.36,
        "TT SELL": 22.65,
        "BILL BUY": 21.34,
        "BILL SELL": 22.69,
        "TC BUY": 0.0,
        "TC SELL": 0.0,
        "CN BUY": 20.75,
        "CN SELL": 23.05,
        "PC BUY": 21.33
    },
    {
        "CURRENCY": "SOUTH AFRICAN RAND",
        "SYMBOL": "ZAR/INR",
        "TT BUY": 4.38,
        "TT SELL": 4.64,
        "BILL BUY": 4.37,
        "BILL SELL": 4.65,
        "TC BUY": 0.0,
        "TC SELL": 0.0,
        "CN BUY": 4.2,
        "CN SELL": 4.75,
        "PC BUY": 4.36
    },
    {
        "CURRENCY": "CHINESE YUAN",
        "SYMBOL": "CNY/INR",
        "TT BUY": 0.0,
        "TT SELL": 0.0,
        "BILL BUY": 11.2,
        "BILL SELL": 11.52,
        "TC BUY": 0.0,
        "TC SELL": 0.0,
        "CN BUY": 0.0,
        "CN SELL": 0.0,
        "PC BUY": 0.0
    },
    {
        "CURRENCY": "OMANI RIYAL",
        "SYMBOL": "OMR/INR",
        "TT BUY": 208.5,
        "TT SELL": 221.1,
        "BILL BUY": 208.36,
        "BILL SELL": 221.55,
        "TC BUY": 0.0,
        "TC SELL": 0.0,
        "CN BUY": 202.5,
        "CN SELL": 224.9,
        "PC BUY": 0.0
    },
    {
        "CURRENCY": "QATARI RIAL",
        "SYMBOL": "QAR/INR",
        "TT BUY": 22.04,
        "TT SELL": 23.38,
        "BILL BUY": 22.03,
        "BILL SELL": 23.42,
        "TC BUY": 0.0,
        "TC SELL": 0.0,
        "CN BUY": 21.4,
        "CN SELL": 23.75,
        "PC BUY": 22.01
    },
    {
        "CURRENCY": "MALAYSIAN RINGGIT",
        "SYMBOL": "MYR/INR",
        "TT BUY": 0.0,
        "TT SELL": 0.0,
        "BILL BUY": 0.0,
        "BILL SELL": 0.0,
        "TC BUY": 0.0,
        "TC SELL": 0.0,
        "CN BUY": 16.25,
        "CN SELL": 18.4,
        "PC BUY": 0.0
    },
    {
        "CURRENCY": "THAI BAHT",
        "SYMBOL": "THB/INR",
        "TT BUY": 0.0,
        "TT SELL": 0.0,
        "BILL BUY": 0.0,
        "BILL SELL": 0.0,
        "TC BUY": 0.0,
        "TC SELL": 0.0,
        "CN BUY": 206.3,
        "CN SELL": 229.8,
        "PC BUY": 0.0
    },
    {
        "CURRENCY": "PAKISTANI RUPEE",
        "SYMBOL": "PKR/INR",
        "TT BUY": 0.0,
        "TT SELL": 0.0,
        "BILL BUY": 0.0,
        "BILL SELL": 0.0,
        "TC BUY": 0.0,
        "TC SELL": 0.0,
        "CN BUY": 0.31,
        "CN SELL": 0.37,
        "PC BUY": 0.0
    },
    {
        "CURRENCY": "BANGLADESHI TAKA",
        "SYMBOL": "BDT/INR",
        "TT BUY": 0.0,
        "TT SELL": 0.0,
        "BILL BUY": 0.0,
        "BILL SELL": 0.0,
        "TC BUY": 0.0,
        "TC SELL": 0.0,
        "CN BUY": 0.67,
        "CN SELL": 0.82,
        "PC BUY": 0.0
    },
    {
        "CURRENCY": "TURKISH LIRA",
        "SYMBOL": "TRY/INR",
        "TT BUY": 0.0,
        "TT SELL": 0.0,
        "BILL BUY": 4.31,
        "BILL SELL": 4.57,
        "TC BUY": 0.0,
        "TC SELL": 0.0,
        "CN BUY": 0.0,
        "CN SELL": 0.0,
        "PC BUY": 0.0
    },
    {
        "CURRENCY": "KOREAN WON",
        "SYMBOL": "KRW/INR",
        "TT BUY": 0.0,
        "TT SELL": 0.0,
        "BILL BUY": 5.64,
        "BILL SELL": 6.0,
        "TC BUY": 0.0,
        "TC SELL": 0.0,
        "CN BUY": 0.0,
        "CN SELL": 0.0,
        "PC BUY": 0.0
    }
]