[
    {
        "CURRENCY": "UNITED STATES DOLLAR",
        "SYMBOL": "USD/INR",
        "TT BUY": 80.13,
        "TT SELL": 81.63,
        "BILL BUY": 80.06,
        "BILL SELL": 81.8,
        "TC BUY": 79.4,
        "TC SELL": 82.05,
        "CN BUY": 79.1,
        "CN SELL": 82.2,
        "PC BUY": 80.0
    },
    {
        "CURRENCY": "EURO",
        "SYMBOL": "EUR/INR",
        "TT BUY": 81.52,
        "TT SELL": 84.33,
        "BILL BUY": 81.46,
        "BILL SELL": 84.5,
        "TC BUY": 80.75,
        "TC SELL": 84.75,
        "CN BUY": 80.35,
        "CN SELL": 84.95,
        "PC BUY": 81.4
    },
    {
        "CURRENCY": "GREAT BRITAIN POUND",
        "SYMBOL": "GBP/INR",
        "TT BUY": 93.34,
        "TT SELL": 96.38,
        "BILL BUY": 93.27,
        "BILL SELL": 96.56,
        "TC BUY": 92.45,
        "TC SELL": 96.85,
        "CN BUY": 92.0,
        "CN SELL": 97.1,
        "PC BUY": 93.2
    },
    {
        "CURRENCY": "JAPANESE YEN",
        "SYMBOL": "JPY/INR",
        "TT BUY": 56.59,
        "TT SELL": 58.29,
        "BILL BUY": 56.55,
        "BILL SELL": 58.41,
        "TC BUY": 56.05,
        "TC SELL": 58.6,
        "CN BUY": 53.9,
        "CN SELL": 60.5,
        "PC BUY": 56.51
    },
    {
        "CURRENCY": "SWISS FRANC",
        "SYMBOL": "CHF/INR",
        "TT BUY": 82.68,
        "TT SELL": 85.58,
        "BILL BUY": 82.62,
        "BILL SELL": 85.74,
        "TC BUY": 81.9,
        "TC SELL": 86.0,
        "CN BUY": 78.75,
        "CN SELL": 88.8,
        "PC BUY": 82.56
    },
    {
        "CURRENCY": "AUSTRALIAN DOLLAR",
        "SYMBOL": "AUD/INR",
        "TT BUY": 52.76,
        "TT SELL": 54.98,
        "BILL BUY": 52.72,
        "BILL SELL": 55.09,
        "TC BUY": 52.8,
        "TC SELL": 55.25,
        "CN BUY": 50.75,
        "CN SELL": 57.05,
        "PC BUY": 52.68
    },
    {
        "CURRENCY": "NEW ZEALAND DOLLAR",
        "SYMBOL": "NZD/INR",
        "TT BUY": 47.95,
        "TT SELL": 50.13,
        "BILL BUY": 47.92,
        "BILL SELL": 50.23,
        "TC BUY": 0.0,
        "TC SELL": 0.0,
        "CN BUY": 45.65,
        "CN SELL": 52.05,
        "PC BUY": 47.88
    },
    {
        "CURRENCY": "CANADIAN DOLLAR",
        "SYMBOL": "CAD/INR",
        "TT BUY": 59.81,
        "TT SELL": 61.71,
        "BILL BUY": 59.77,
        "BILL SELL": 61.83,
        "TC BUY": 59.25,
        "TC SELL": 62.0,
        "CN BUY": 56.95,
        "CN SELL": 64.0,
        "PC BUY": 59.72
    },
    {
        "CURRENCY": "SINGAPORE DOLLAR",
        "SYMBOL": "SGD/INR",
        "TT BUY": 57.79,
        "TT SELL": 59.55,
        "BILL BUY": 57.74,
        "BILL SELL": 59.66,
        "TC BUY": 0.0,
        "TC SELL": 0.0,
        "CN BUY": 55.05,
        "CN SELL": 61.8,
        "PC BUY": 57.7
    },
    {
        "CURRENCY": "HONG KONG DOLLAR",
        "SYMBOL": "HKD/INR",
        "TT BUY": 10.15,
        "TT SELL": 10.48,
        "BILL BUY": 10.14,
        "BILL SELL": 10.5,
        "TC BUY": 0.0,
        "TC SELL": 0.0,
        "CN BUY": 9.65,
        "CN SELL": 10.9,
        "PC BUY": 10.12
    },
    {
        "CURRENCY": "DANISH KRONER",
        "SYMBOL": "DKK/INR",
        "TT BUY": 10.98,
        "TT SELL": 11.32,
        "BILL BUY": 10.97,
        "BILL SELL": 11.34,
        "TC BUY": 0.0,
        "TC SELL": 0.0,
        "CN BUY": 10.45,
        "CN SELL": 11.7,
        "PC BUY": 10.96
    },
    {
        "CURRENCY": "NORWEGIAN KRONER",
        "SYMBOL": "NOK/INR",
        "TT BUY": 7.94,
        "TT SELL": 8.17,
        "BILL BUY": 7.93,
        "BILL SELL": 8.18,
        "TC BUY": 0.0,
        "TC SELL": 0.0,
        "CN BUY": 7.55,
        "CN SELL": 8.45,
        "PC BUY": 7.91
    },
    {
        "CURRENCY": "SWEDISH KRONA",
        "SYMBOL": "SEK/INR",
        "TT BUY": 7.58,
        "TT SELL": 7.8,
        "BILL BUY": 7.57,
        "BILL SELL": 7.82,
        "TC BUY": 0.0,
        "TC SELL": 0.0,
        "CN BUY": 7.2,
        "CN SELL": 8.1,
        "PC BUY": 7.55
    },
    {
        "CURRENCY": "BAHRAINI DINAR",
        "SYMBOL": "BHD/INR",
        "TT BUY": 208.4,
        "TT SELL": 221.05,
        "BILL BUY": 208.21,
        "BILL SELL": 221.48,
        "TC BUY": 0.0,
        "TC SELL": 0.0,
        "CN BUY": 202.5,
        "CN SELL": 224.8,
        "PC BUY": 208.06
    },
    {
        "CURRENCY": "KUWAITI DINAR",
        "SYMBOL": "KWD/INR",
        "TT BUY": 255.4,
        "TT SELL": 270.93,
        "BILL BUY": 255.19,
        "BILL SELL": 271.46,
        "TC BUY": 0.0,
        "TC SELL": 0.0,
        "CN BUY": 248.2,
        "CN SELL": 275.5,
        "PC BUY": 255.0
    },
    {
        "CURRENCY": "UAE DIRHAM",
        "SYMBOL": "AED/INR",
        "TT BUY": 21.38,
        "TT SELL": 22.68,
        "BILL BUY": 21.37,
        "BILL SELL": 22.73,
        "TC BUY": 0.0,
        "TC SELL": 0.0,
        "CN BUY": 20.8,
        "CN SELL": 23.05,
        "PC BUY": 21.35
    },
    {
        "CURRENCY": "SAUDI ARABIAN RIYAL",
        "SYMBOL": "SAR/INR",
        "TT BUY": 20.89,
        "TT SELL": 22.16,
        "BILL BUY": 20.87,
        "BILL SELL": 22.21,
        "TC BUY": 0.0,
        "TC SELL": 0.0,
        "CN BUY": 20.3,
        "CN SELL": 22.55,
        "PC BUY": 20.86
    },
    {
        "CURRENCY": "SOUTH AFRICAN RAND",
        "SYMBOL": "ZAR/INR",
        "TT BUY": 4.54,
        "TT SELL": 4.82,
        "BILL BUY": 4.53,
        "BILL SELL": 4.83,
        "TC BUY": 0.0,
        "TC SELL": 0.0,
        "CN BUY": 4.35,
        "CN SELL": 4.9,
        "PC BUY": 4.52
    },
    {
        "CURRENCY": "CHINESE YUAN",
        "SYMBOL": "CNY/INR",
        "TT BUY": 0.0,
        "TT SELL": 0.0,
        "BILL BUY": 11.21,
        "BILL SELL": 11.54,
        "TC BUY": 0.0,
        "TC SELL": 0.0,
        "CN BUY": 0.0,
        "CN SELL": 0.0,
        "PC BUY": 0.0
    },
    {
        "CURRENCY": "OMANI RIYAL",
        "SYMBOL": "OMR/INR",
        "TT BUY": 204.0,
        "TT SELL": 216.94,
        "BILL BUY": 203.87,
        "BILL SELL": 217.37,
        "TC BUY": 0.0,
        "TC SELL": 0.0,
        "CN BUY": 198.3,
        "CN SELL": 220.6,
        "PC BUY": 0.0
    },
    {
        "CURRENCY": "QATARI RIAL",
        "SYMBOL": "QAR/INR",
        "TT BUY": 21.38,
        "TT SELL": 22.89,
        "BILL BUY": 21.36,
        "BILL SELL": 22.93,
        "TC BUY": 0.0,
        "TC SELL": 0.0,
        "CN BUY": 20.8,
        "CN SELL": 23.25,
        "PC BUY": 21.35
    },
    {
        "CURRENCY": "MALAYSIAN RINGGIT",
        "SYMBOL": "MYR/INR",
        "TT BUY": 0.0,
        "TT SELL": 0.0,
        "BILL BUY": 0.0,
        "BILL SELL": 0.0,
        "TC BUY": 0.0,
        "TC SELL": 0.0,
        "CN BUY": 16.35,
        "CN SELL": 18.5,
        "PC BUY": 0.0
    },
    {
        "CURRENCY": "THAI BAHT",
        "SYMBOL": "THB/INR",
        "TT BUY": 0.0,
        "TT SELL": 0.0,
        "BILL BUY": 0.0,
        "BILL SELL": 0.0,
        "TC BUY": 0.0,
        "TC SELL": 0.0,
        "CN BUY": 211.5,
        "CN SELL": 235.6,
        "PC BUY": 0.0
    },
    {
        "CURRENCY": "PAKISTANI RUPEE",
        "SYMBOL": "PKR/INR",
        "TT BUY": 0.0,
        "TT SELL": 0.0,
        "BILL BUY": 0.0,
        "BILL SELL": 0.0,
        "TC BUY": 0.0,
        "TC SELL": 0.0,
        "CN BUY": 0.3,
        "CN SELL": 0.36,
        "PC BUY": 0.0
    },
    {
        "CURRENCY": "BANGLADESHI TAKA",
        "SYMBOL": "BDT/INR",
        "TT BUY": 0.0,
        "TT SELL": 0.0,
        "BILL BUY": 0.0,
        "BILL SELL": 0.0,
        "TC BUY": 0.0,
        "TC SELL": 0.0,
        "CN BUY": 0.66,
        "CN SELL": 0.8,
        "PC BUY": 0.0
    },
    {
        "CURRENCY": "TURKISH LIRA",
        "SYMBOL": "TRY/INR",
        "TT BUY": 0.0,
        "TT SELL": 0.0,
        "BILL BUY": 4.23,
        "BILL SELL": 4.49,
        "TC BUY": 0.0,
        "TC SELL": 0.0,
        "CN BUY": 0.0,
        "CN SELL": 0.0,
        "PC BUY": 0.0
    },
    {
        "CURRENCY": "KOREAN WON",
        "SYMBOL": "KRW/INR",
        "TT BUY": 0.0,
        "TT SELL": 0.0,
        "BILL BUY": 5.94,
        "BILL SELL": 6.32,
        "TC BUY": 0.0,
        "TC SELL": 0.0,
        "CN BUY": 0.0,
        "CN SELL": 0.0,
        "PC BUY": 0.0
    }
]