[
    {
        "CURRENCY": "UNITED STATES DOLLAR",
        "SYMBOL": "USD/INR",
        "TT BUY": 76.45,
        "TT SELL": 77.95,
        "BILL BUY": 76.39,
        "BILL SELL": 78.12,
        "TC BUY": 75.7,
        "TC SELL": 78.35,
        "CN BUY": 75.4,
        "CN SELL": 78.5,
        "PC BUY": 76.34
    },
    {
        "CURRENCY": "EURO",
        "SYMBOL": "EUR/INR",
        "TT BUY": 79.97,
        "TT SELL": 82.75,
        "BILL BUY": 79.9,
        "BILL SELL": 82.92,
        "TC BUY": 79.2,
        "TC SELL": 83.15,
        "CN BUY": 78.8,
        "CN SELL": 83.35,
        "PC BUY": 79.85
    },
    {
        "CURRENCY": "GREAT BRITAIN POUND",
        "SYMBOL": "GBP/INR",
        "TT BUY": 93.77,
        "TT SELL": 96.79,
        "BILL BUY": 93.69,
        "BILL SELL": 96.99,
        "TC BUY": 92.85,
        "TC SELL": 97.25,
        "CN BUY": 92.4,
        "CN SELL": 97.5,
        "PC BUY": 93.63
    },
    {
        "CURRENCY": "JAPANESE YEN",
        "SYMBOL": "JPY/INR",
        "TT BUY": 58.3,
        "TT SELL": 60.15,
        "BILL BUY": 58.25,
        "BILL SELL": 60.28,
        "TC BUY": 57.75,
        "TC SELL": 60.45,
        "CN BUY": 55.5,
        "CN SELL": 62.4,
        "PC BUY": 58.21
    },
    {
        "CURRENCY": "SWISS FRANC",
        "SYMBOL": "CHF/INR",
        "TT BUY": 76.22,
        "TT SELL": 78.95,
        "BILL BUY": 76.16,
        "BILL SELL": 79.11,
        "TC BUY": 75.5,
        "TC SELL": 79.35,
        "CN BUY": 72.6,
        "CN SELL": 81.95,
        "PC BUY": 76.11
    },
    {
        "CURRENCY": "AUSTRALIAN DOLLAR",
        "SYMBOL": "AUD/INR",
        "TT BUY": 52.67,
        "TT SELL": 54.84,
        "BILL BUY": 52.63,
        "BILL SELL": 54.96,
        "TC BUY": 52.65,
        "TC SELL": 55.1,
        "CN BUY": 50.6,
        "CN SELL": 56.9,
        "PC BUY": 52.59
    },
    {
        "CURRENCY": "NEW ZEALAND DOLLAR",
        "SYMBOL": "NZD/INR",
        "TT BUY": 47.82,
        "TT SELL": 49.93,
        "BILL BUY": 47.78,
        "BILL SELL": 50.04,
        "TC BUY": 0.0,
        "TC SELL": 0.0,
        "CN BUY": 45.5,
        "CN SELL": 51.85,
        "PC BUY": 47.75
    },
    {
        "CURRENCY": "CANADIAN DOLLAR",
        "SYMBOL": "CAD/INR",
        "TT BUY": 58.4,
        "TT SELL": 60.32,
        "BILL BUY": 58.36,
        "BILL SELL": 60.44,
        "TC BUY": 57.8,
        "TC SELL": 60.6,
        "CN BUY": 55.55,
        "CN SELL": 62.55,
        "PC BUY": 58.31
    },
    {
        "CURRENCY": "SINGAPORE DOLLAR",
        "SYMBOL": "SGD/INR",
        "TT BUY": 54.74,
        "TT SELL": 56.43,
        "BILL BUY": 54.7,
        "BILL SELL": 56.55,
        "TC BUY": 0.0,
        "TC SELL": 0.0,
        "CN BUY": 52.1,
        "CN SELL": 58.55,
        "PC BUY": 54.66
    },
    {
        "CURRENCY": "HONG KONG DOLLAR",
        "SYMBOL": "HKD/INR",
        "TT BUY": 9.68,
        "TT SELL": 9.99,
        "BILL BUY": 9.66,
        "BILL SELL": 10.02,
        "TC BUY": 0.0,
        "TC SELL": 0.0,
        "CN BUY": 9.2,
        "CN SELL": 10.4,
        "PC BUY": 9.65
    },
    {
        "CURRENCY": "DANISH KRONER",
        "SYMBOL": "DKK/INR",
        "TT BUY": 10.77,
        "TT SELL": 11.11,
        "BILL BUY": 10.75,
        "BILL SELL": 11.14,
        "TC BUY": 0.0,
        "TC SELL": 0.0,
        "CN BUY": 10.25,
        "CN SELL": 11.5,
        "PC BUY": 10.75
    },
    {
        "CURRENCY": "NORWEGIAN KRONER",
        "SYMBOL": "NOK/INR",
        "TT BUY": 7.83,
        "TT SELL": 8.07,
        "BILL BUY": 7.82,
        "BILL SELL": 8.09,
        "TC BUY": 0.0,
        "TC SELL": 0.0,
        "CN BUY": 7.45,
        "CN SELL": 8.35,
        "PC BUY": 7.8
    },
    {
        "CURRENCY": "SWEDISH KRONA",
        "SYMBOL": "SEK/INR",
        "TT BUY": 7.56,
        "TT SELL": 7.8,
        "BILL BUY": 7.55,
        "BILL SELL": 7.81,
        "TC BUY": 0.0,
        "TC SELL": 0.0,
        "CN BUY": 7.15,
        "CN SELL": 8.1,
        "PC BUY": 7.53
    },
    {
        "CURRENCY": "BAHRAINI DINAR",
        "SYMBOL": "BHD/INR",
        "TT BUY": 198.8,
        "TT SELL": 211.0,
        "BILL BUY": 198.63,
        "BILL SELL": 211.43,
        "TC BUY": 0.0,
        "TC SELL": 0.0,
        "CN BUY": 193.1,
        "CN SELL": 214.6,
        "PC BUY": 198.48
    },
    {
        "CURRENCY": "KUWAITI DINAR",
        "SYMBOL": "KWD/INR",
        "TT BUY": 244.1,
        "TT SELL": 259.29,
        "BILL BUY": 243.95,
        "BILL SELL": 259.82,
        "TC BUY": 0.0,
        "TC SELL": 0.0,
        "CN BUY": 237.1,
        "CN SELL": 263.7,
        "PC BUY": 243.77
    },
    {
        "CURRENCY": "UAE DIRHAM",
        "SYMBOL": "AED/INR",
        "TT BUY": 20.4,
        "TT SELL": 21.66,
        "BILL BUY": 20.39,
        "BILL SELL": 21.71,
        "TC BUY": 0.0,
        "TC SELL": 0.0,
        "CN BUY": 19.8,
        "CN SELL": 22.05,
        "PC BUY": 20.37
    },
    {
        "CURRENCY": "SAUDI ARABIAN RIYAL",
        "SYMBOL": "SAR/INR",
        "TT BUY": 19.98,
        "TT SELL": 21.21,
        "BILL BUY": 19.97,
        "BILL SELL": 21.25,
        "TC BUY": 0.0,
        "TC SELL": 0.0,
        "CN BUY": 19.4,
        "CN SELL": 21.55,
        "PC BUY": 19.95
    },
    {
        "CURRENCY": "SOUTH AFRICAN RAND",
        "SYMBOL": "ZAR/INR",
        "TT BUY": 4.65,
        "TT SELL": 4.94,
        "BILL BUY": 4.65,
        "BILL SELL": 4.95,
        "TC BUY": 0.0,
        "TC SELL": 0.0,
        "CN BUY": 4.45,
        "CN SELL": 5.05,
        "PC BUY": 4.63
    },
    {
        "CURRENCY": "CHINESE YUAN",
        "SYMBOL": "CNY/INR",
        "TT BUY": 0.0,
        "TT SELL": 0.0,
        "BILL BUY": 11.31,
        "BILL SELL": 11.66,
        "TC BUY": 0.0,
        "TC SELL": 0.0,
        "CN BUY": 0.0,
        "CN SELL": 0.0,
        "PC BUY": 0.0
    },
    {
        "CURRENCY": "OMANI RIYAL",
        "SYMBOL": "OMR/INR",
        "TT BUY": 194.7,
        "TT SELL": 206.63,
        "BILL BUY": 194.51,
        "BILL SELL": 207.06,
        "TC BUY": 0.0,
        "TC SELL": 0.0,
        "CN BUY": 189.1,
        "CN SELL": 210.2,
        "PC BUY": 0.0
    },
    {
        "CURRENCY": "QATARI RIAL",
        "SYMBOL": "QAR/INR",
        "TT BUY": 20.51,
        "TT SELL": 21.78,
        "BILL BUY": 20.49,
        "BILL SELL": 21.82,
        "TC BUY": 0.0,
        "TC SELL": 0.0,
        "CN BUY": 19.9,
        "CN SELL": 22.15,
        "PC BUY": 20.48
    },
    {
        "CURRENCY": "MALAYSIAN RINGGIT",
        "SYMBOL": "MYR/INR",
        "TT BUY": 0.0,
        "TT SELL": 0.0,
        "BILL BUY": 0.0,
        "BILL SELL": 0.0,
        "TC BUY": 0.0,
        "TC SELL": 0.0,
        "CN BUY": 16.45,
        "CN SELL": 18.65,
        "PC BUY": 0.0
    },
    {
        "CURRENCY": "THAI BAHT",
        "SYMBOL": "THB/INR",
        "TT BUY": 0.0,
        "TT SELL": 0.0,
        "BILL BUY": 0.0,
        "BILL SELL": 0.0,
        "TC BUY": 0.0,
        "TC SELL": 0.0,
        "CN BUY": 209.7,
        "CN SELL": 233.8,
        "PC BUY": 0.0
    },
    {
        "CURRENCY": "PAKISTANI RUPEE",
        "SYMBOL": "PKR/INR",
        "TT BUY": 0.0,
        "TT SELL": 0.0,
        "BILL BUY": 0.0,
        "BILL SELL": 0.0,
        "TC BUY": 0.0,
        "TC SELL": 0.0,
        "CN BUY": 0.34,
        "CN SELL": 0.41,
        "PC BUY": 0.0
    },
    {
        "CURRENCY": "BANGLADESHI TAKA",
        "SYMBOL": "BDT/INR",
        "TT BUY": 0.0,
        "TT SELL": 0.0,
        "BILL BUY": 0.0,
        "BILL SELL": 0.0,
        "TC BUY": 0.0,
        "TC SELL": 0.0,
        "CN BUY": 0.74,
        "CN SELL": 0.89,
        "PC BUY": 0.0
    },
    {
        "CURRENCY": "TURKISH LIRA",
        "SYMBOL": "TRY/INR",
        "TT BUY": 0.0,
        "TT SELL": 0.0,
        "BILL BUY": 4.88,
        "BILL SELL": 5.19,
        "TC BUY": 0.0,
        "TC SELL": 0.0,
        "CN BUY": 0.0,
        "CN SELL": 0.0,
        "PC BUY": 0.0
    },
    {
        "CURRENCY": "KOREAN WON",
        "SYMBOL": "KRW/INR",
        "TT BUY": 0.0,
        "TT SELL": 0.0,
        "BILL BUY": 5.86,
        "BILL SELL": 6.24,
        "TC BUY": 0.0,
        "TC SELL": 0.0,
        "CN BUY": 0.0,
        "CN SELL": 0.0,
        "PC BUY": 0.0
    }
]