[
    {
        "CURRENCY": "UNITED STATES DOLLAR",
        "SYMBOL": "USD/INR",
        "TT BUY": 82.15,
        "TT SELL": 83.65,
        "BILL BUY": 82.08,
        "BILL SELL": 83.82,
        "TC BUY": 81.4,
        "TC SELL": 84.1,
        "CN BUY": 81.0,
        "CN SELL": 84.3,
        "PC BUY": 82.02
    },
    {
        "CURRENCY": "EURO",
        "SYMBOL": "EUR/INR",
        "TT BUY": 79.68,
        "TT SELL": 82.46,
        "BILL BUY": 79.62,
        "BILL SELL": 82.62,
        "TC BUY": 78.9,
        "TC SELL": 82.85,
        "CN BUY": 78.5,
        "CN SELL": 83.05,
        "PC BUY": 79.56
    },
    {
        "CURRENCY": "GREAT BRITAIN POUND",
        "SYMBOL": "GBP/INR",
        "TT BUY": 91.42,
        "TT SELL": 94.42,
        "BILL BUY": 91.36,
        "BILL SELL": 94.61,
        "TC BUY": 90.55,
        "TC SELL": 94.9,
        "CN BUY": 90.1,
        "CN SELL": 95.15,
        "PC BUY": 91.28
    },
    {
        "CURRENCY": "JAPANESE YEN",
        "SYMBOL": "JPY/INR",
        "TT BUY": 54.38,
        "TT SELL": 55.97,
        "BILL BUY": 54.34,
        "BILL SELL": 56.08,
        "TC BUY": 53.85,
        "TC SELL": 56.25,
        "CN BUY": 51.75,
        "CN SELL": 58.1,
        "PC BUY": 54.3
    },
    {
        "CURRENCY": "SWISS FRANC",
        "SYMBOL": "CHF/INR",
        "TT BUY": 81.09,
        "TT SELL": 83.84,
        "BILL BUY": 81.03,
        "BILL SELL": 84.01,
        "TC BUY": 80.3,
        "TC SELL": 84.25,
        "CN BUY": 77.2,
        "CN SELL": 87.0,
        "PC BUY": 80.97
    },
    {
        "CURRENCY": "AUSTRALIAN DOLLAR",
        "SYMBOL": "AUD/INR",
        "TT BUY": 51.01,
        "TT SELL": 53.17,
        "BILL BUY": 50.97,
        "BILL SELL": 53.28,
        "TC BUY": 51.05,
        "TC SELL": 53.45,
        "CN BUY": 49.1,
        "CN SELL": 55.2,
        "PC BUY": 50.93
    },
    {
        "CURRENCY": "NEW ZEALAND DOLLAR",
        "SYMBOL": "NZD/INR",
        "TT BUY": 46.12,
        "TT SELL": 48.28,
        "BILL BUY": 46.09,
        "BILL SELL": 48.38,
        "TC BUY": 0.0,
        "TC SELL": 0.0,
        "CN BUY": 43.9,
        "CN SELL": 50.1,
        "PC BUY": 46.05
    },
    {
        "CURRENCY": "CANADIAN DOLLAR",
        "SYMBOL": "CAD/INR",
        "TT BUY": 59.26,
        "TT SELL": 61.1,
        "BILL BUY": 59.22,
        "BILL SELL": 61.22,
        "TC BUY": 58.7,
        "TC SELL": 61.4,
        "CN BUY": 56.45,
        "CN SELL": 63.4,
        "PC BUY": 59.17
    },
    {
        "CURRENCY": "SINGAPORE DOLLAR",
        "SYMBOL": "SGD/INR",
        "TT BUY": 57.3,
        "TT SELL": 59.01,
        "BILL BUY": 57.26,
        "BILL SELL": 59.13,
        "TC BUY": 0.0,
        "TC SELL": 0.0,
        "CN BUY": 54.55,
        "CN SELL": 61.25,
        "PC BUY": 57.21
    },
    {
        "CURRENCY": "HONG KONG DOLLAR",
        "SYMBOL": "HKD/INR",
        "TT BUY": 10.4,
        "TT SELL": 10.73,
        "BILL BUY": 10.39,
        "BILL SELL": 10.75,
        "TC BUY": 0.0,
        "TC SELL": 0.0,
        "CN BUY": 9.9,
        "CN SELL": 11.15,
        "PC BUY": 10.37
    },
    {
        "CURRENCY": "DANISH KRONER",
        "SYMBOL": "DKK/INR",
        "TT BUY": 10.74,
        "TT SELL": 11.05,
        "BILL BUY": 10.72,
        "BILL SELL": 11.08,
        "TC BUY": 0.0,
        "TC SELL": 0.0,
        "CN BUY": 10.2,
        "CN SELL": 11.45,
        "PC BUY": 10.72
    },
    {
        "CURRENCY": "NORWEGIAN KRONER",
        "SYMBOL": "NOK/INR",
        "TT BUY": 7.66,
        "TT SELL": 7.88,
        "BILL BUY": 7.64,
        "BILL SELL": 7.9,
        "TC BUY": 0.0,
        "TC SELL": 0.0,
        "CN BUY": 7.25,
        "CN SELL": 8.15,
        "PC BUY": 7.63
    },
    {
        "CURRENCY": "SWEDISH KRONA",
        "SYMBOL": "SEK/INR",
        "TT BUY": 7.24,
        "TT SELL": 7.45,
        "BILL BUY": 7.23,
        "BILL SELL": 7.47,
        "TC BUY": 0.0,
        "TC SELL": 0.0,
        "CN BUY": 6.85,
        "CN SELL": 7.75,
        "PC BUY": 7.21
    },
    {
        "CURRENCY": "BAHRAINI DINAR",
        "SYMBOL": "BHD/INR",
        "TT BUY": 213.6,
        "TT SELL": 226.47,
        "BILL BUY": 213.42,
        "BILL SELL": 226.93,
        "TC BUY": 0.0,
        "TC SELL": 0.0,
        "CN BUY": 207.6,
        "CN SELL": 230.4,
        "PC BUY": 213.26
    },
    {
        "CURRENCY": "KUWAITI DINAR",
        "SYMBOL": "KWD/INR",
        "TT BUY": 259.2,
        "TT SELL": 275.15,
        "BILL BUY": 259.0,
        "BILL SELL": 275.7,
        "TC BUY": 0.0,
        "TC SELL": 0.0,
        "CN BUY": 251.9,
        "CN SELL": 279.9,
        "PC BUY": 258.8
    },
    {
        "CURRENCY": "UAE DIRHAM",
        "SYMBOL": "AED/INR",
        "TT BUY": 21.92,
        "TT SELL": 23.25,
        "BILL BUY": 21.91,
        "BILL SELL": 23.29,
        "TC BUY": 0.0,
        "TC SELL": 0.0,
        "CN BUY": 21.3,
        "CN SELL": 23.65,
        "PC BUY": 21.89
    },
    {
        "CURRENCY": "SAUDI ARABIAN RIYAL",
        "SYMBOL": "SAR/INR",
        "TT BUY": 21.42,
        "TT SELL": 22.72,
        "BILL BUY": 21.4,
        "BILL SELL": 22.77,
        "TC BUY": 0.0,
        "TC SELL": 0.0,
        "CN BUY": 20.8,
        "CN SELL": 23.1,
        "PC BUY": 21.39
    },
    {
        "CURRENCY": "SOUTH AFRICAN RAND",
        "SYMBOL": "ZAR/INR",
        "TT BUY": 4.39,
        "TT SELL": 4.66,
        "BILL BUY": 4.38,
        "BILL SELL": 4.67,
        "TC BUY": 0.0,
        "TC SELL": 0.0,
        "CN BUY": 4.25,
        "CN SELL": 4.75,
        "PC BUY": 4.37
    },
    {
        "CURRENCY": "CHINESE YUAN",
        "SYMBOL": "CNY/INR",
        "TT BUY": 0.0,
        "TT SELL": 0.0,
        "BILL BUY": 11.28,
        "BILL SELL": 11.61,
        "TC BUY": 0.0,
        "TC SELL": 0.0,
        "CN BUY": 0.0,
        "CN SELL": 0.0,
        "PC BUY": 0.0
    },
    {
        "CURRENCY": "OMANI RIYAL",
        "SYMBOL": "OMR/INR",
        "TT BUY": 209.2,
        "TT SELL": 221.76,
        "BILL BUY": 208.99,
        "BILL SELL": 222.21,
        "TC BUY": 0.0,
        "TC SELL": 0.0,
        "CN BUY": 203.3,
        "CN SELL": 225.6,
        "PC BUY": 0.0
    },
    {
        "CURRENCY": "QATARI RIAL",
        "SYMBOL": "QAR/INR",
        "TT BUY": 22.11,
        "TT SELL": 23.45,
        "BILL BUY": 22.1,
        "BILL SELL": 23.49,
        "TC BUY": 0.0,
        "TC SELL": 0.0,
        "CN BUY": 21.5,
        "CN SELL": 23.85,
        "PC BUY": 22.08
    },
    {
        "CURRENCY": "MALAYSIAN RINGGIT",
        "SYMBOL": "MYR/INR",
        "TT BUY": 0.0,
        "TT SELL": 0.0,
        "BILL BUY": 0.0,
        "BILL SELL": 0.0,
        "TC BUY": 0.0,
        "TC SELL": 0.0,
        "CN BUY": 16.35,
        "CN SELL": 18.5,
        "PC BUY": 0.0
    },
    {
        "CURRENCY": "THAI BAHT",
        "SYMBOL": "THB/INR",
        "TT BUY": 0.0,
        "TT SELL": 0.0,
        "BILL BUY": 0.0,
        "BILL SELL": 0.0,
        "TC BUY": 0.0,
        "TC SELL": 0.0,
        "CN BUY": 203.8,
        "CN SELL": 226.8,
        "PC BUY": 0.0
    },
    {
        "CURRENCY": "PAKISTANI RUPEE",
        "SYMBOL": "PKR/INR",
        "TT BUY": 0.0,
        "TT SELL": 0.0,
        "BILL BUY": 0.0,
        "BILL SELL": 0.0,
        "TC BUY": 0.0,
        "TC SELL": 0.0,
        "CN BUY": 0.31,
        "CN SELL": 0.37,
        "PC BUY": 0.0
    },
    {
        "CURRENCY": "BANGLADESHI TAKA",
        "SYMBOL": "BDT/INR",
        "TT BUY": 0.0,
        "TT SELL": 0.0,
        "BILL BUY": 0.0,
        "BILL SELL": 0.0,
        "TC BUY": 0.0,
        "TC SELL": 0.0,
        "CN BUY": 0.68,
        "CN SELL": 0.82,
        "PC BUY": 0.0
    },
    {
        "CURRENCY": "TURKISH LIRA",
        "SYMBOL": "TRY/INR",
        "TT BUY": 0.0,
        "TT SELL": 0.0,
        "BILL BUY": 4.32,
        "BILL SELL": 4.6,
        "TC BUY": 0.0,
        "TC SELL": 0.0,
        "CN BUY": 0.0,
        "CN SELL": 0.0,
        "PC BUY": 0.0
    },
    {
        "CURRENCY": "KOREAN WON",
        "SYMBOL": "KRW/INR",
        "TT BUY": 0.0,
        "TT SELL": 0.0,
        "BILL BUY": 5.6,
        "BILL SELL": 5.95,
        "TC BUY": 0.0,
        "TC SELL": 0.0,
        "CN BUY": 0.0,
        "CN SELL": 0.0,
        "PC BUY": 0.0
    }
]